LICENSE
README.md
setup.py
Project/Unused_object.py
Project/__init__.py
Project/__main__.py
Project/common_functions.py
Project/main.py
Project/main_classes.py
Project/url_scraper_classes.py
Project/weather_scraper_classes.py
Project/wikipedia_scraper_classes.py
test/test__main__.py
test/test_common_functions.py
test/test_main_classes.py
test/test_url_scraper_classes.py
test/test_weather_scraper_classes.py
test/test_wikipedia_scraper_classes.py
url_scraper.egg-info/PKG-INFO
url_scraper.egg-info/SOURCES.txt
url_scraper.egg-info/dependency_links.txt
url_scraper.egg-info/requires.txt
url_scraper.egg-info/top_level.txt