Metadata-Version: 1.1
Name: url-scraper
Version: 1.0
Summary: scrapes the weather page for urls
Home-page: https://github.com/hjasmith1996/Project_2-v2.git
Author: Harry Smith
Author-email: hjasmith1996@gmail.com
License: BSD 2-clause
Platform: UNKNOWN
Classifier: Development Status :: 1 - Planning
Classifier: Intended Audience :: Science/Research
Classifier: License :: OSI Approved :: BSD License
Classifier: Operating System :: POSIX :: Linux
Classifier: Programming Language :: Python :: 2
Classifier: Programming Language :: Python :: 2.7
Classifier: Programming Language :: Python :: 3
Classifier: Programming Language :: Python :: 3.4
Classifier: Programming Language :: Python :: 3.5
